Workbook

Sheet README
A1: SentinelPay: cost, earned value and ROI model
A3: Currency: US dollars. All amounts are ASSUMPTIONS for planning, not quotes. Replace them with your real rates and prices.
A4: Blue text on the Assumptions, Labor and EVM sheets = inputs you edit. Yellow fill = the key levers. Black = formulas. Green = links to other sheets.
A5: Assumptions: every rate, price and volume lives there. Change a cell and every sheet recalculates.
A6: Labor: monthly loaded rate per role and FTE per month for the 6-month build.
A7: Budget: monthly cost baseline, contingency, management reserve, and cumulative Planned Value (PV).
A8: EVM: enter % complete and actual cost each month; CPI, SPI, EAC, ETC, VAC and TCPI calculate. Months 1-3 hold ILLUSTRATIVE numbers; overwrite them.
A9: ROI: 36-month cash model (6 months build, then selling). Summary: payback month, NPV, IRR, ROI.
A10: Adoption factor (Assumptions B23) scales customer wins: 1.0 = base case, 0.5 = half as many customers.
A11: Customer volumes and prices are placeholders. Do not present the ROI as a forecast until you validate them with real buyers.

Sheet Summary
A1: Investment and return summary
A3: Measure | B3: Value | C3: How to read it
A4: Build investment incl. reserve ($) | B4: =SUM(ROI!H4:H39) -> 738333.75 | C4: Cash spent in the 6-month program
A5: Cost baseline BAC ($) | B5: =Budget!H18 -> 703175 | C5: Used for earned value
A6: First month with positive net cash | B6: =IF(COUNT(ROI!R4:R39)=0,"Not within 36 months",MIN(ROI!R4:R39)) -> 10 | C6: Month the product first earns more than it costs to run
A7: Payback month (cumulative cash turns positive) | B7: =IF(COUNT(ROI!Q4:Q39)=0,"Not within 36 months",MIN(ROI!Q4:Q39)) -> 18 | C7: Month counted from project start; go-live is month 6
A8: Months of selling needed to pay back | B8: =IF(ISNUMBER(B7),B7-Assumptions!B22,"n/a") -> 12 | C8: Payback month minus go-live month
A9: Peak funding need ($) | B9: =-MIN(ROI!N4:N39) -> 833504.18 | C9: Most cash you must fund before it turns
A10: Net cash at month 36 ($) | B10: =ROI!N39 -> 8457623.8 | C10: Cumulative
A11: ROI over 36 months | B11: =IF(B4=0,0,ROI!N39/B4) -> 11.455015 | C11: Net cash at month 36 divided by build investment
A12: NPV at discount rate ($) | B12: =SUM(ROI!P4:P39) -> 6350335.6 | C12: Discount rate on Assumptions B5
A13: IRR (annualised) | B13: =IFERROR((1+IRR(ROI!M4:M39,0.02))^12-1,"n/a") -> 2.7928223 | C13: From monthly cash flows
A14: Active customers at month 36 | B14: =ROI!D39 -> 62.797607 | C14: After churn
A15: Annual recurring revenue at month 36 ($) | B15: =ROI!D39*Assumptions!B12 -> 9419641 | C15: Active customers x annual subscription
A18: Adoption sensitivity (SNAPSHOT of values at build time; change Assumptions B23 to re-run live)
A19: Adoption factor | B19: Payback month | C19: Net cash month 36 ($) | D19: NPV ($) | E19: Peak funding need ($) | F19: Customers month 36
A20: 1 | B20: 18 | C20: 8457624 | D20: 6350336 | E20: 833504 | F20: 62.8
A21: 0.5 | B21: 27 | C21: 2409645 | D21: 1627651 | E21: 1074077 | F21: 31.4
A22: 0.25 | B22: Not within 36 months | C22: -614344 | D22: -733691 | E22: 1449722 | F22: 15.7

Sheet Assumptions
A1: Assumptions (edit blue cells)
A2: Item | B2: Value | C2: Note
A3: Contingency (% of subtotal) | B3: 0.1 | C3: Known-unknowns; inside the cost baseline
A4: Management reserve (% of baseline) | B4: 0.05 | C4: Unknown-unknowns; held outside the baseline, released by the sponsor
A5: Discount rate (annual) | B5: 0.12 | C5: Assumed cost of capital
A6: Cloud dev/test per month ($) | B6: 3000 | C6: Azure + AWS standby test environments
A7: Tooling and licences per month ($) | B7: 2000 | C7: CI, scanners, observability
A8: Penetration test, one-off in month 5 ($) | B8: 25000 | C8: Independent vendor
A9: Compliance audit preparation, month 5 ($) | B9: 30000 | C9: PCI DSS / privacy readiness assessment
A10: Legal and privacy review, month 2 ($) | B10: 10000 | C10: DPIA, contracts, data-processing terms
A11: Documentation and training, month 6 ($) | B11: 8000 | C11: Customer docs, admin training
A12: Annual subscription per customer ($) | B12: 150000 | C12: PLACEHOLDER price: validate with buyers
A13: Onboarding fee per customer ($, one-off) | B13: 60000 | C13: PLACEHOLDER: integration and go-live support
A14: Run cost per customer per month ($) | B14: 2500 | C14: Cloud, support share, gateway fees not passed through
... A20: Annual customer churn | B20: 0.05 | C20: Assumed
A21: Monthly churn (calculated) | B21: =1-(1-B20)^(1/12) -> 0.0042653188 | C21: Derived from annual churn
A22: Go-live month | B22: 6 | C22: End of the 6-month program
A23: Adoption factor | B23: 1 | C23: Scales customer wins. 1.0 = base, 0.5 = pessimistic

Sheet Labor
A1: Labor plan: FTE per month (edit blue cells)
A3: Role | B3: Loaded rate $/month | C3: M1 | D3: M2 | E3: M3 | F3: M4 | G3: M5 | H3: M6 | I3: FTE-months | J3: Cost ($)
A4: Program manager | B4: 9000 | C4: 1 | D4: 1 | E4: 1 | F4: 1 | G4: 1 | H4: 1 | I4: =SUM(C4:H4) -> 6 | J4: =B4*I4 -> 54000
A5: Principal architect | B5: 14000 | C5: 1 | D5: 1 | E5: 1 | F5: 1 | G5: 0.5 | H5: 0.5 | I5: =SUM(C5:H5) -> 5 | J5: =B5*I5 -> 70000
A6: Backend engineers (.NET) | B6: 8000 | C6: 2 | D6: 3 | E6: 3 | F6: 3 | G6: 2 | H6: 2 | I6: =SUM(C6:H6) -> 15 | J6: =B6*I6 -> 120000
A7: Flutter engineers | B7: 7500 | C7: 1 | D7: 2 | E7: 2 | F7: 2 | G7: 2 | H7: 1 | I7: =SUM(C7:H7) -> 10 | J7: =B7*I7 -> 75000
A8: AI / agent engineer | B8: 10000 | C8: 0.5 | D8: 0.5 | E8: 1 | F8: 1 | G8: 1 | H8: 0.5 | I8: =SUM(C8:H8) -> 4.5 | J8: =B8*I8 -> 45000
A9: QA / SDET | B9: 6000 | C9: 0.5 | D9: 1 | E9: 2 | F9: 2 | G9: 2 | H9: 2 | I9: =SUM(C9:H9) -> 9.5 | J9: =B9*I9 -> 57000
A10: DevOps / SRE | B10: 9000 | C10: 1 | D10: 1 | E10: 1 | F10: 1 | G10: 1 | H10: 1 | I10: =SUM(C10:H10) -> 6 | J10: =B10*I10 -> 54000
A11: Security and compliance | B11: 10000 | C11: 0.5 | D11: 0.5 | E11: 0.5 | F11: 0.5 | G11: 1 | H11: 0.5 | I11: =SUM(C11:H11) -> 3.5 | J11: =B11*I11 -> 35000
A12: UX and accessibility | B12: 7000 | C12: 0.5 | D12: 1 | E12: 0.5 | F12: 1 | G12: 0.5 | H12: 0.25 | I12: =SUM(C12:H12) -> 3.75 | J12: =B12*I12 -> 26250
A13: Total | C13: =SUM(C4:C12) -> 8 | D13: =SUM(D4:D12) -> 11 | E13: =SUM(E4:E12) -> 12 | F13: =SUM(F4:F12) -> 12.5 | G13: =SUM(G4:G12) -> 11 | H13: =SUM(H4:H12) -> 8.75 | I13: =SUM(I4:I12) -> 63.25 | J13: =SUM(J4:J12) -> 536250
A14: Labor cost by month ($) | C14: =SUMPRODUCT($B$4:$B$12,C4:C12) -> 72000 | D14: =SUMPRODUCT($B$4:$B$12,D4:D12) -> 94000 | E14: =SUMPRODUCT($B$4:$B$12,E4:E12) -> 101500 | F14: =SUMPRODUCT($B$4:$B$12,F4:F12) -> 105000 | G14: =SUMPRODUCT($B$4:$B$12,G4:G12) -> 91500 | H14: =SUMPRODUCT($B$4:$B$12,H4:H12) -> 72250 | J14: =SUM(C14:H14) -> 536250
A16: Rates are assumed loaded costs (salary, overhead). Replace with your own. Check: J13 should equal J14.

Sheet Budget
A1: Cost baseline and Planned Value ($)
A3: Line | B3: M1 | C3: M2 | D3: M3 | E3: M4 | F3: M5 | G3: M6 | H3: Total
A4: Labor | B4: =Labor!C14 -> 72000 | C4: =Labor!D14 -> 94000 | D4: =Labor!E14 -> 101500 | E4: =Labor!F14 -> 105000 | F4: =Labor!G14 -> 91500 | G4: =Labor!H14 -> 72250 | H4: =SUM(B4:G4) -> 536250
A5: Cloud dev/test | B5: =Assumptions!$B$6 -> 3000 | C5: =Assumptions!$B$6 -> 3000 | D5: =Assumptions!$B$6 -> 3000 | E5: =Assumptions!$B$6 -> 3000 | F5: =Assumptions!$B$6 -> 3000 | G5: =Assumptions!$B$6 -> 3000 | H5: =SUM(B5:G5) -> 18000
A6: Tooling and licences | B6: =Assumptions!$B$7 -> 2000 | C6: =Assumptions!$B$7 -> 2000 | D6: =Assumptions!$B$7 -> 2000 | E6: =Assumptions!$B$7 -> 2000 | F6: =Assumptions!$B$7 -> 2000 | G6: =Assumptions!$B$7 -> 2000 | H6: =SUM(B6:G6) -> 12000
A7: Legal and privacy review | B7: 0 | C7: =Assumptions!$B$10 -> 10000 | D7: 0 | E7: 0 | F7: 0 | G7: 0 | H7: =SUM(B7:G7) -> 10000
A8: Penetration test | B8: 0 | C8: 0 | D8: 0 | E8: 0 | F8: =Assumptions!$B$8 -> 25000 | G8: 0 | H8: =SUM(B8:G8) -> 25000
A9: Compliance audit prep | B9: 0 | C9: 0 | D9: 0 | E9: 0 | F9: =Assumptions!$B$9 -> 30000 | G9: 0 | H9: =SUM(B9:G9) -> 30000
A10: Documentation and training | B10: 0 | C10: 0 | D10: 0 | E10: 0 | F10: 0 | G10: =Assumptions!$B$11 -> 8000 | H10: =SUM(B10:G10) -> 8000
A11: Subtotal | B11: =SUM(B4:B10) -> 77000 | C11: =SUM(C4:C10) -> 109000 | D11: =SUM(D4:D10) -> 106500 | E11: =SUM(E4:E10) -> 110000 | F11: =SUM(F4:F10) -> 151500 | G11: =SUM(G4:G10) -> 85250 | H11: =SUM(B11:G11) -> 639250
A12: Contingency | B12: =B11*Assumptions!$B$3 -> 7700 | C12: =C11*Assumptions!$B$3 -> 10900 | D12: =D11*Assumptions!$B$3 -> 10650 | E12: =E11*Assumptions!$B$3 -> 11000 | F12: =F11*Assumptions!$B$3 -> 15150 | G12: =G11*Assumptions!$B$3 -> 8525 | H12: =SUM(B12:G12) -> 63925
A13: Monthly baseline (PV, monthly) | B13: =B11+B12 -> 84700 | C13: =C11+C12 -> 119900 | D13: =D11+D12 -> 117150 | E13: =E11+E12 -> 121000 | F13: =F11+F12 -> 166650 | G13: =G11+G12 -> 93775 | H13: =SUM(B13:G13) -> 703175
A14: Cumulative PV | B14: =SUM($B$13:B13) -> 84700 | C14: =SUM($B$13:C13) -> 204600 | D14: =SUM($B$13:D13) -> 321750 | E14: =SUM($B$13:E13) -> 442750 | F14: =SUM($B$13:F13) -> 609400 | G14: =SUM($B$13:G13) -> 703175
A15: Management reserve | B15: =B13*Assumptions!$B$4 -> 4235 | C15: =C13*Assumptions!$B$4 -> 5995 | D15: =D13*Assumptions!$B$4 -> 5857.5 | E15: =E13*Assumptions!$B$4 -> 6050 | F15: =F13*Assumptions!$B$4 -> 8332.5 | G15: =G13*Assumptions!$B$4 -> 4688.75 | H15: =SUM(B15:G15) -> 35158.75
A16: Total funding incl. reserve | B16: =B13+B15 -> 88935 | C16: =C13+C15 -> 125895 | D16: =D13+D15 -> 123007.5 | E16: =E13+E15 -> 127050 | F16: =F13+F15 -> 174982.5 | G16: =G13+G15 -> 98463.75 | H16: =SUM(B16:G16) -> 738333.75
A18: BAC (Budget At Completion) = H13 | H18: =H13 -> 703175
A19: Management reserve is held outside BAC and is not used in EVM.

Sheet EVM
A1: Earned value tracker (enter blue cells monthly)
A2: Months 1-3 below are ILLUSTRATIVE numbers to show the formulas working. Overwrite with real % complete and actual cost.
A4: Month | B4: PV (cum) | C4: % complete (cum) | D4: EV (cum) | E4: AC (cum) | F4: CV = EV-AC | G4: SV = EV-PV | H4: CPI | I4: SPI | J4: EAC = BAC/CPI | K4: ETC | L4: VAC = BAC-EAC | M4: TCPI
A5: M1 | B5: =Budget!B14 -> 84700 | C5: 0.118 | D5: =IF($C5="","",$C5*Budget!$H$18) -> 82974.65 | E5: 86400 | F5: =IF(OR($C5="",$E5=""),"",D5-E5) -> -3425.35 | G5: =IF($C5="","",D5-B5) -> -1725.35 | H5: =IF(OR($C5="",N(E5)=0),"",D5/E5) -> 0.96035475 | I5: =IF(OR($C5="",B5=0),"",D5/B5) -> 0.97962987 | J5: =IF(OR(H5="",N(H5)=0),"",Budget!$H$18/H5) -> 732203.39 | K5: =IF(J5="","",J5-E5) -> 645803.39 | L5: =IF(J5="","",Budget!$H$18-J5) -> -29028.39 | M5: =IF(OR($C5="",$E5="",Budget!$H$18-E5=0),"",(Budget!$H$18-D5)/(Budget!$H$18-E5)) -> 1.0055536
A6: M2 | B6: =Budget!C14 -> 204600 | C6: 0.285 | D6: =IF($C6="","",$C6*Budget!$H$18) -> 200404.88 | E6: 208700 | F6: =IF(OR($C6="",$E6=""),"",D6-E6) -> -8295.125 | G6: =IF($C6="","",D6-B6) -> -4195.125 | H6: =IF(OR($C6="",N(E6)=0),"",D6/E6) -> 0.96025335 | I6: =IF(OR($C6="",B6=0),"",D6/B6) -> 0.97949597 | J6: =IF(OR(H6="",N(H6)=0),"",Budget!$H$18/H6) -> 732280.7 | K6: =IF(J6="","",J6-E6) -> 523580.7 | L6: =IF(J6="","",Budget!$H$18-J6) -> -29105.702 | M6: =IF(OR($C6="",$E6="",Budget!$H$18-E6=0),"",(Budget!$H$18-D6)/(Budget!$H$18-E6)) -> 1.0167756
A7: M3 | B7: =Budget!D14 -> 321750 | C7: 0.448 | D7: =IF($C7="","",$C7*Budget!$H$18) -> 315022.4 | E7: 328200 | F7: =IF(OR($C7="",$E7=""),"",D7-E7) -> -13177.6 | G7: =IF($C7="","",D7-B7) -> -6727.6 | H7: =IF(OR($C7="",N(E7)=0),"",D7/E7) -> 0.95984887 | I7: =IF(OR($C7="",B7=0),"",D7/B7) -> 0.9790906 | J7: =IF(OR(H7="",N(H7)=0),"",Budget!$H$18/H7) -> 732589.29 | K7: =IF(J7="","",J7-E7) -> 404389.29 | L7: =IF(J7="","",Budget!$H$18-J7) -> -29414.286 | M7: =IF(OR($C7="",$E7="",Budget!$H$18-E7=0),"",(Budget!$H$18-D7)/(Budget!$H$18-E7)) -> 1.0351426
A8: M4 | B8: =Budget!E14 -> 442750 | D8: =IF($C8="","",$C8*Budget!$H$18) | F8: =IF(OR($C8="",$E8=""),"",D8-E8) | G8: =IF($C8="","",D8-B8) | H8: =IF(OR($C8="",N(E8)=0),"",D8/E8) | I8: =IF(OR($C8="",B8=0),"",D8/B8) | J8: =IF(OR(H8="",N(H8)=0),"",Budget!$H$18/H8) | K8: =IF(J8="","",J8-E8) | L8: =IF(J8="","",Budget!$H$18-J8) | M8: =IF(OR($C8="",$E8="",Budget!$H$18-E8=0),"",(Budget!$H$18-D8)/(Budget!$H$18-E8))
A9: M5 | B9: =Budget!F14 -> 609400 | D9: =IF($C9="","",$C9*Budget!$H$18) | F9: =IF(OR($C9="",$E9=""),"",D9-E9) | G9: =IF($C9="","",D9-B9) | H9: =IF(OR($C9="",N(E9)=0),"",D9/E9) | I9: =IF(OR($C9="",B9=0),"",D9/B9) | J9: =IF(OR(H9="",N(H9)=0),"",Budget!$H$18/H9) | K9: =IF(J9="","",J9-E9) | L9: =IF(J9="","",Budget!$H$18-J9) | M9: =IF(OR($C9="",$E9="",Budget!$H$18-E9=0),"",(Budget!$H$18-D9)/(Budget!$H$18-E9))
A10: M6 | B10: =Budget!G14 -> 703175 | D10: =IF($C10="","",$C10*Budget!$H$18) | F10: =IF(OR($C10="",$E10=""),"",D10-E10) | G10: =IF($C10="","",D10-B10) | H10: =IF(OR($C10="",N(E10)=0),"",D10/E10) | I10: =IF(OR($C10="",B10=0),"",D10/B10) | J10: =IF(OR(H10="",N(H10)=0),"",Budget!$H$18/H10) | K10: =IF(J10="","",J10-E10) | L10: =IF(J10="","",Budget!$H$18-J10) | M10: =IF(OR($C10="",$E10="",Budget!$H$18-E10=0),"",(Budget!$H$18-D10)/(Budget!$H$18-E10))
A12: Reading the numbers
A13: CPI below 1.00 = over budget for the work done. SPI below 1.00 = behind schedule.
A14: EAC = BAC / CPI assumes today's cost efficiency continues. VAC negative = forecast overrun.
A15: TCPI above 1.10 means the remaining work must be done much more efficiently than so far: escalate.
A16: Thresholds used in the project plan: amber below 0.95, red below 0.90 for CPI or SPI.

Sheet ROI
A1: 36-month cash model
A3: Month | B3: Phase | C3: New customers | D3: Active customers | E3: Subscription revenue | F3: Onboarding revenue | G3: Total revenue | H3: Build cost | I3: Customer run cost | J3: Sustain team | K3: Sales and marketing | L3: Total cost | M3: Net cash | N3: Cumulative net cash | O3: Discount factor | P3: Discounted net | Q3: Payback flag | R3: Positive-month flag
A4: 1 | B4: =IF(A4<=Assumptions!$B$22,"Build","Selling") -> Build | C4: =IF(A4<=Assumptions!$B$22,0,IF(A4<=12,Assumptions!$B$17,IF(A4<=24,Assumptions!$B$18,Assumptions!$B$19)))*Assumptions!$B$23 -> 0 | D4: =C4 -> 0 | E4: =D4*Assumptions!$B$12/12 -> 0 | F4: =C4*Assumptions!$B$13 -> 0 | G4: =E4+F4 -> 0 | H4: =IF(A4<=Assumptions!$B$22,INDEX(Budget!$B$16:$G$16,A4),0) -> 88935 | I4: =D4*Assumptions!$B$14 -> 0 | J4: =IF(A4>Assumptions!$B$22,Assumptions!$B$15,0) -> 0 | K4: =IF(A4>=5,Assumptions!$B$16,0) -> 0 | L4: =H4+I4+J4+K4 -> 88935 | M4: =G4-L4 -> -88935 | N4: =M4 -> -88935 | O4: =1/(1+Assumptions!$B$5)^(A4/12) -> 0.9906004 | P4: =M4*O4 -> -88099.046 | Q4: =IF(AND(N4>=0,A4>Assumptions!$B$22),A4,"") | R4: =IF(AND(M4>0,A4>Assumptions!$B$22),A4,"")
A5: 2 | B5: =IF(A5<=Assumptions!$B$22,"Build","Selling") -> Build | C5: =IF(A5<=Assumptions!$B$22,0,IF(A5<=12,Assumptions!$B$17,IF(A5<=24,Assumptions!$B$18,Assumptions!$B$19)))*Assumptions!$B$23 -> 0 | D5: =D4*(1-Assumptions!$B$21)+C5 -> 0 | E5: =D5*Assumptions!$B$12/12 -> 0 | F5: =C5*Assumptions!$B$13 -> 0 | G5: =E5+F5 -> 0 | H5: =IF(A5<=Assumptions!$B$22,INDEX(Budget!$B$16:$G$16,A5),0) -> 125895 | I5: =D5*Assumptions!$B$14 -> 0 | J5: =IF(A5>Assumptions!$B$22,Assumptions!$B$15,0) -> 0 | K5: =IF(A5>=5,Assumptions!$B$16,0) -> 0 | L5: =H5+I5+J5+K5 -> 125895 | M5: =G5-L5 -> -125895 | N5: =N4+M5 -> -214830 | O5: =1/(1+Assumptions!$B$5)^(A5/12) -> 0.98128915 | P5: =M5*O5 -> -123539.4 | Q5: =IF(AND(N5>=0,A5>Assumptions!$B$22),A5,"") | R5: =IF(AND(M5>0,A5>Assumptions!$B$22),A5,"")
A6: 3 | B6: =IF(A6<=Assumptions!$B$22,"Build","Selling") -> Build | C6: =IF(A6<=Assumptions!$B$22,0,IF(A6<=12,Assumptions!$B$17,IF(A6<=24,Assumptions!$B$18,Assumptions!$B$19)))*Assumptions!$B$23 -> 0 | D6: =D5*(1-Assumptions!$B$21)+C6 -> 0 | E6: =D6*Assumptions!$B$12/12 -> 0 | F6: =C6*Assumptions!$B$13 -> 0 | G6: =E6+F6 -> 0 | H6: =IF(A6<=Assumptions!$B$22,INDEX(Budget!$B$16:$G$16,A6),0) -> 123007.5 | I6: =D6*Assumptions!$B$14 -> 0 | J6: =IF(A6>Assumptions!$B$22,Assumptions!$B$15,0) -> 0 | K6: =IF(A6>=5,Assumptions!$B$16,0) -> 0 | L6: =H6+I6+J6+K6 -> 123007.5 | M6: =G6-L6 -> -123007.5 | N6: =N5+M6 -> -337837.5 | O6: =1/(1+Assumptions!$B$5)^(A6/12) -> 0.97206542 | P6: =M6*O6 -> -119571.34 | Q6: =IF(AND(N6>=0,A6>Assumptions!$B$22),A6,"") | R6: =IF(AND(M6>0,A6>Assumptions!$B$22),A6,"")
A7: 4 | B7: =IF(A7<=Assumptions!$B$22,"Build","Selling") -> Build | C7: =IF(A7<=Assumptions!$B$22,0,IF(A7<=12,Assumptions!$B$17,IF(A7<=24,Assumptions!$B$18,Assumptions!$B$19)))*Assumptions!$B$23 -> 0 | D7: =D6*(1-Assumptions!$B$21)+C7 -> 0 | E7: =D7*Assumptions!$B$12/12 -> 0 | F7: =C7*Assumptions!$B$13 -> 0 | G7: =E7+F7 -> 0 | H7: =IF(A7<=Assumptions!$B$22,INDEX(Budget!$B$16:$G$16,A7),0) -> 127050 | I7: =D7*Assumptions!$B$14 -> 0 | J7: =IF(A7>Assumptions!$B$22,Assumptions!$B$15,0) -> 0 | K7: =IF(A7>=5,Assumptions!$B$16,0) -> 0 | L7: =H7+I7+J7+K7 -> 127050 | M7: =G7-L7 -> -127050 | N7: =N6+M7 -> -464887.5 | O7: =1/(1+Assumptions!$B$5)^(A7/12) -> 0.96292839 | P7: =M7*O7 -> -122340.05 | Q7: =IF(AND(N7>=0,A7>Assumptions!$B$22),A7,"") | R7: =IF(AND(M7>0,A7>Assumptions!$B$22),A7,"")
A8: 5 | B8: =IF(A8<=Assumptions!$B$22,"Build","Selling") -> Build | C8: =IF(A8<=Assumptions!$B$22,0,IF(A8<=12,Assumptions!$B$17,IF(A8<=24,Assumptions!$B$18,Assumptions!$B$19)))*Assumptions!$B$23 -> 0 | D8: =D7*(1-Assumptions!$B$21)+C8 -> 0 | E8: =D8*Assumptions!$B$12/12 -> 0 | F8: =C8*Assumptions!$B$13 -> 0 | G8: =E8+F8 -> 0 | H8: =IF(A8<=Assumptions!$B$22,INDEX(Budget!$B$16:$G$16,A8),0) -> 174982.5 | I8: =D8*Assumptions!$B$14 -> 0 | J8: =IF(A8>Assumptions!$B$22,Assumptions!$B$15,0) -> 0 | K8: =IF(A8>=5,Assumptions!$B$16,0) -> 25000 | L8: =H8+I8+J8+K8 -> 199982.5 | M8: =G8-L8 -> -199982.5 | N8: =N7+M8 -> -664870 | O8: =1/(1+Assumptions!$B$5)^(A8/12) -> 0.95387725 | P8: =M8*O8 -> -190758.76 | Q8: =IF(AND(N8>=0,A8>Assumptions!$B$22),A8,"") | R8: =IF(AND(M8>0,A8>Assumptions!$B$22),A8,"")
A9: 6 | B9: =IF(A9<=Assumptions!$B$22,"Build","Selling") -> Build | C9: =IF(A9<=Assumptions!$B$22,0,IF(A9<=12,Assumptions!$B$17,IF(A9<=24,Assumptions!$B$18,Assumptions!$B$19)))*Assumptions!$B$23 -> 0 | D9: =D8*(1-Assumptions!$B$21)+C9 -> 0 | E9: =D9*Assumptions!$B$12/12 -> 0 | F9: =C9*Assumptions!$B$13 -> 0 | G9: =E9+F9 -> 0 | H9: =IF(A9<=Assumptions!$B$22,INDEX(Budget!$B$16:$G$16,A9),0) -> 98463.75 | I9: =D9*Assumptions!$B$14 -> 0 | J9: =IF(A9>Assumptions!$B$22,Assumptions!$B$15,0) -> 0 | K9: =IF(A9>=5,Assumptions!$B$16,0) -> 25000 | L9: =H9+I9+J9+K9 -> 123463.75 | M9: =G9-L9 -> -123463.75 | N9: =N8+M9 -> -788333.75 | O9: =1/(1+Assumptions!$B$5)^(A9/12) -> 0.94491118 | P9: =M9*O9 -> -116662.28 | Q9: =IF(AND(N9>=0,A9>Assumptions!$B$22),A9,"") | R9: =IF(AND(M9>0,A9>Assumptions!$B$22),A9,"")
A10: 7 | B10: =IF(A10<=Assumptions!$B$22,"Build","Selling") -> Selling | C10: =IF(A10<=Assumptions!$B$22,0,IF(A10<=12,Assumptions!$B$17,IF(A10<=24,Assumptions!$B$18,Assumptions!$B$19)))*Assumptions!$B$23 -> 1 | D10: =D9*(1-Assumptions!$B$21)+C10 -> 1 | E10: =D10*Assumptions!$B$12/12 -> 12500 | F10: =C10*Assumptions!$B$13 -> 60000 | G10: =E10+F10 -> 72500 | H10: =IF(A10<=Assumptions!$B$22,INDEX(Budget!$B$16:$G$16,A10),0) -> 0 | I10: =D10*Assumptions!$B$14 -> 2500 | J10: =IF(A10>Assumptions!$B$22,Assumptions!$B$15,0) -> 70000 | K10: =IF(A10>=5,Assumptions!$B$16,0) -> 25000 | L10: =H10+I10+J10+K10 -> 97500 | M10: =G10-L10 -> -25000 | N10: =N9+M10 -> -813333.75 | O10: =1/(1+Assumptions!$B$5)^(A10/12) -> 0.93602939 | P10: =M10*O10 -> -23400.735 | Q10: =IF(AND(N10>=0,A10>Assumptions!$B$22),A10,"") | R10: =IF(AND(M10>0,A10>Assumptions!$B$22),A10,"")
A11: 8 | B11: =IF(A11<=Assumptions!$B$22,"Build","Selling") -> Selling | C11: =IF(A11<=Assumptions!$B$22,0,IF(A11<=12,Assumptions!$B$17,IF(A11<=24,Assumptions!$B$18,Assumptions!$B$19)))*Assumptions!$B$23 -> 1 | D11: =D10*(1-Assumptions!$B$21)+C11 -> 1.9957347 | E11: =D11*Assumptions!$B$12/12 -> 24946.684 | F11: =C11*Assumptions!$B$13 -> 60000 | G11: =E11+F11 -> 84946.684 | H11: =IF(A11<=Assumptions!$B$22,INDEX(Budget!$B$16:$G$16,A11),0) -> 0 | I11: =D11*Assumptions!$B$14 -> 4989.3367 | J11: =IF(A11>Assumptions!$B$22,Assumptions!$B$15,0) -> 70000 | K11: =IF(A11>=5,Assumptions!$B$16,0) -> 25000 | L11: =H11+I11+J11+K11 -> 99989.337 | M11: =G11-L11 -> -15042.653 | N11: =N10+M11 -> -828376.4 | O11: =1/(1+Assumptions!$B$5)^(A11/12) -> 0.92723109 | P11: =M11*O11 -> -13948.016 | Q11: =IF(AND(N11>=0,A11>Assumptions!$B$22),A11,"") | R11: =IF(AND(M11>0,A11>Assumptions!$B$22),A11,"")
A12: 9 | B12: =IF(A12<=Assumptions!$B$22,"Build","Selling") -> Selling | C12: =IF(A12<=Assumptions!$B$22,0,IF(A12<=12,Assumptions!$B$17,IF(A12<=24,Assumptions!$B$18,Assumptions!$B$19)))*Assumptions!$B$23 -> 1 | D12: =D11*(1-Assumptions!$B$21)+C12 -> 2.9872222 | E12: =D12*Assumptions!$B$12/12 -> 37340.278 | F12: =C12*Assumptions!$B$13 -> 60000 | G12: =E12+F12 -> 97340.278 | H12: =IF(A12<=Assumptions!$B$22,INDEX(Budget!$B$16:$G$16,A12),0) -> 0 | I12: =D12*Assumptions!$B$14 -> 7468.0556 | J12: =IF(A12>Assumptions!$B$22,Assumptions!$B$15,0) -> 70000 | K12: =IF(A12>=5,Assumptions!$B$16,0) -> 25000 | L12: =H12+I12+J12+K12 -> 102468.06 | M12: =G12-L12 -> -5127.7776 | N12: =N11+M12 -> -833504.18 | O12: =1/(1+Assumptions!$B$5)^(A12/12) -> 0.91851549 | P12: =M12*O12 -> -4709.9432 | Q12: =IF(AND(N12>=0,A12>Assumptions!$B$22),A12,"") | R12: =IF(AND(M12>0,A12>Assumptions!$B$22),A12,"")
A13: 10 | B13: =IF(A13<=Assumptions!$B$22,"Build","Selling") -> Selling | C13: =IF(A13<=Assumptions!$B$22,0,IF(A13<=12,Assumptions!$B$17,IF(A13<=24,Assumptions!$B$18,Assumptions!$B$19)))*Assumptions!$B$23 -> 1 | D13: =D12*(1-Assumptions!$B$21)+C13 -> 3.9744808 | E13: =D13*Assumptions!$B$12/12 -> 49681.01 | F13: =C13*Assumptions!$B$13 -> 60000 | G13: =E13+F13 -> 109681.01 | H13: =IF(A13<=Assumptions!$B$22,INDEX(Budget!$B$16:$G$16,A13),0) -> 0 | I13: =D13*Assumptions!$B$14 -> 9936.202 | J13: =IF(A13>Assumptions!$B$22,Assumptions!$B$15,0) -> 70000 | K13: =IF(A13>=5,Assumptions!$B$16,0) -> 25000 | L13: =H13+I13+J13+K13 -> 104936.2 | M13: =G13-L13 -> 4744.8078 | N13: =N12+M13 -> -828759.37 | O13: =1/(1+Assumptions!$B$5)^(A13/12) -> 0.90988181 | P13: =M13*O13 -> 4317.2143 | Q13: =IF(AND(N13>=0,A13>Assumptions!$B$22),A13,"") | R13: =IF(AND(M13>0,A13>Assumptions!$B$22),A13,"") -> 10
A14: 11 | B14: =IF(A14<=Assumptions!$B$22,"Build","Selling") -> Selling | C14: =IF(A14<=Assumptions!$B$22,0,IF(A14<=12,Assumptions!$B$17,IF(A14<=24,Assumptions!$B$18,Assumptions!$B$19)))*Assumptions!$B$23 -> 1 | D14: =D13*(1-Assumptions!$B$21)+C14 -> 4.9575284 | E14: =D14*Assumptions!$B$12/12 -> 61969.104 | F14: =C14*Assumptions!$B$13 -> 60000 | G14: =E14+F14 -> 121969.1 | H14: =IF(A14<=Assumptions!$B$22,INDEX(Budget!$B$16:$G$16,A14),0) -> 0 | I14: =D14*Assumptions!$B$14 -> 12393.821 | J14: =IF(A14>Assumptions!$B$22,Assumptions!$B$15,0) -> 70000 | K14: =IF(A14>=5,Assumptions!$B$16,0) -> 25000 | L14: =H14+I14+J14+K14 -> 107393.82 | M14: =G14-L14 -> 14575.284 | N14: =N13+M14 -> -814184.09 | O14: =1/(1+Assumptions!$B$5)^(A14/12) -> 0.90132928 | P14: =M14*O14 -> 13137.13 | Q14: =IF(AND(N14>=0,A14>Assumptions!$B$22),A14,"") | R14: =IF(AND(M14>0,A14>Assumptions!$B$22),A14,"") -> 11
A15: 12 | B15: =IF(A15<=Assumptions!$B$22,"Build","Selling") -> Selling | C15: =IF(A15<=Assumptions!$B$22,0,IF(A15<=12,Assumptions!$B$17,IF(A15<=24,Assumptions!$B$18,Assumptions!$B$19)))*Assumptions!$B$23 -> 1 | D15: =D14*(1-Assumptions!$B$21)+C15 -> 5.9363829 | E15: =D15*Assumptions!$B$12/12 -> 74204.786 | F15: =C15*Assumptions!$B$13 -> 60000 | G15: =E15+F15 -> 134204.79 | H15: =IF(A15<=Assumptions!$B$22,INDEX(Budget!$B$16:$G$16,A15),0) -> 0 | I15: =D15*Assumptions!$B$14 -> 14840.957 | J15: =IF(A15>Assumptions!$B$22,Assumptions!$B$15,0) -> 70000 | K15: =IF(A15>=5,Assumptions!$B$16,0) -> 25000 | L15: =H15+I15+J15+K15 -> 109840.96 | M15: =G15-L15 -> 24363.829 | N15: =N14+M15 -> -789820.26 | O15: =1/(1+Assumptions!$B$5)^(A15/12) -> 0.89285714 | P15: =M15*O15 -> 21753.419 | Q15: =IF(AND(N15>=0,A15>Assumptions!$B$22),A15,"") | R15: =IF(AND(M15>0,A15>Assumptions!$B$22),A15,"") -> 12
A16: 13 | B16: =IF(A16<=Assumptions!$B$22,"Build","Selling") -> Selling | C16: =IF(A16<=Assumptions!$B$22,0,IF(A16<=12,Assumptions!$B$17,IF(A16<=24,Assumptions!$B$18,Assumptions!$B$19)))*Assumptions!$B$23 -> 2 | D16: =D15*(1-Assumptions!$B$21)+C16 -> 7.9110623 | E16: =D16*Assumptions!$B$12/12 -> 98888.279 | F16: =C16*Assumptions!$B$13 -> 120000 | G16: =E16+F16 -> 218888.28 | H16: =IF(A16<=Assumptions!$B$22,INDEX(Budget!$B$16:$G$16,A16),0) -> 0 | I16: =D16*Assumptions!$B$14 -> 19777.656 | J16: =IF(A16>Assumptions!$B$22,Assumptions!$B$15,0) -> 70000 | K16: =IF(A16>=5,Assumptions!$B$16,0) -> 25000 | L16: =H16+I16+J16+K16 -> 114777.66 | M16: =G16-L16 -> 104110.62 | N16: =N15+M16 -> -685709.64 | O16: =1/(1+Assumptions!$B$5)^(A16/12) -> 0.88446464 | P16: =M16*O16 -> 92082.165 | Q16: =IF(AND(N16>=0,A16>Assumptions!$B$22),A16,"") | R16: =IF(AND(M16>0,A16>Assumptions!$B$22),A16,"") -> 13
... A39: 36 | B39: =IF(A39<=Assumptions!$B$22,"Build","Selling") -> Selling | C39: =IF(A39<=Assumptions!$B$22,0,IF(A39<=12,Assumptions!$B$17,IF(A39<=24,Assumptions!$B$18,Assumptions!$B$19)))*Assumptions!$B$23 -> 3 | D39: =D38*(1-Assumptions!$B$21)+C39 -> 62.797607 | E39: =D39*Assumptions!$B$12/12 -> 784970.08 | F39: =C39*Assumptions!$B$13 -> 180000 | G39: =E39+F39 -> 964970.08 | H39: =IF(A39<=Assumptions!$B$22,INDEX(Budget!$B$16:$G$16,A39),0) -> 0 | I39: =D39*Assumptions!$B$14 -> 156994.02 | J39: =IF(A39>Assumptions!$B$22,Assumptions!$B$15,0) -> 70000 | K39: =IF(A39>=5,Assumptions!$B$16,0) -> 25000 | L39: =H39+I39+J39+K39 -> 251994.02 | M39: =G39-L39 -> 712976.07 | N39: =N38+M39 -> 8457623.8 | O39: =1/(1+Assumptions!$B$5)^(A39/12) -> 0.71178025 | P39: =M39*O39 -> 507482.28 | Q39: =IF(AND(N39>=0,A39>Assumptions!$B$22),A39,"") -> 36 | R39: =IF(AND(M39>0,A39>Assumptions!$B$22),A39,"") -> 36
